requests_chef/__about__.py
requests_chef/__init__.py
requests_chef/mixlib_auth.py
requests_chef-0.1.7.dist-info/DESCRIPTION.rst
requests_chef-0.1.7.dist-info/METADATA
requests_chef-0.1.7.dist-info/RECORD
requests_chef-0.1.7.dist-info/WHEEL
requests_chef-0.1.7.dist-info/dependency_links.txt
requests_chef-0.1.7.dist-info/metadata.json
requests_chef-0.1.7.dist-info/top_level.txt
