Metadata-Version: 2.0
Name: requests-chef
Version: 0.1.7
Summary: Chef Authentication protocol support for Python-Requests
Home-page: https://github.com/samstav/requests-chef
Author: Sam Stavinoha
Author-email: samuel.stavinoha@rackspace.com
License: Apache License, Version 2.0
Keywords: opscode chef requests authentication auth c7ecfbd5
Platform: UNKNOWN
Classifier: Intended Audience :: Developers
Classifier: License :: OSI Approved :: Apache Software License
Classifier: Operating System :: OS Independent
Classifier: Topic :: Software Development
Classifier: Development Status :: 4 - Beta
Classifier: Programming Language :: Python
Classifier: Programming Language :: Python :: 2
Classifier: Programming Language :: Python :: 2.7
Classifier: Programming Language :: Python :: 3
Classifier: Programming Language :: Python :: 3.4
Requires-Dist: cryptography (==1.3.1f)
Requires-Dist: requests (>=2.7.0)
Requires-Dist: six (>=1.9.0)
